shopify_prefect_tasks/__init__.py
shopify_prefect_tasks/_version.py
shopify_prefect_tasks/collect.py
shopify_prefect_tasks/collection.py
shopify_prefect_tasks/custom_collection.py
shopify_prefect_tasks/customer.py
shopify_prefect_tasks/customer_address.py
shopify_prefect_tasks/graphql.py
shopify_prefect_tasks/inventory_items.py
shopify_prefect_tasks/inventory_levels.py
shopify_prefect_tasks/locations.py
shopify_prefect_tasks/order.py
shopify_prefect_tasks/product.py
shopify_prefect_tasks/variant.py
shopify_prefect_tasks-0.1.0.dist-info/LICENSE
shopify_prefect_tasks-0.1.0.dist-info/METADATA
shopify_prefect_tasks-0.1.0.dist-info/WHEEL
shopify_prefect_tasks-0.1.0.dist-info/top_level.txt
shopify_prefect_tasks-0.1.0.dist-info/RECORD
