Metadata-Version: 2.1
Name: shopify-prefect-tasks
Version: 0.1.0
Home-page: https://github.com/aporacloudmobile/shopify_prefect_tasks
Author: Carlos Paiva
Author-email: carlospaiva87@gmail.com
Classifier: Programming Language :: Python :: 3
Classifier: Operating System :: OS Independent
Requires-Python: >=3.6
License-File: LICENSE
Requires-Dist: requests (<2.27.0)
Requires-Dist: jsonmerge (==1.9.0)
Requires-Dist: versioneer (==0.28)
Requires-Dist: setuptools (==67.1.0)
Requires-Dist: pytest (==7.2.1)
Requires-Dist: prefect (==0.15.11)
Requires-Dist: shopifyAPI (==12.2.0)
Requires-Dist: boto3 (==1.26.61)
Requires-Dist: botocore (==1.29.61)
